odoo/addons/account_edi_proxy_client_peppol/README.rst
odoo/addons/account_edi_proxy_client_peppol/__init__.py
odoo/addons/account_edi_proxy_client_peppol/__manifest__.py
odoo/addons/account_edi_proxy_client_peppol/data/neutralize.sql
odoo/addons/account_edi_proxy_client_peppol/i18n/account_edi_proxy_client.pot
odoo/addons/account_edi_proxy_client_peppol/i18n/ar.po
odoo/addons/account_edi_proxy_client_peppol/i18n/az.po
odoo/addons/account_edi_proxy_client_peppol/i18n/bg.po
odoo/addons/account_edi_proxy_client_peppol/i18n/ca.po
odoo/addons/account_edi_proxy_client_peppol/i18n/cs.po
odoo/addons/account_edi_proxy_client_peppol/i18n/da.po
odoo/addons/account_edi_proxy_client_peppol/i18n/de.po
odoo/addons/account_edi_proxy_client_peppol/i18n/el.po
odoo/addons/account_edi_proxy_client_peppol/i18n/es.po
odoo/addons/account_edi_proxy_client_peppol/i18n/es_419.po
odoo/addons/account_edi_proxy_client_peppol/i18n/et.po
odoo/addons/account_edi_proxy_client_peppol/i18n/fa.po
odoo/addons/account_edi_proxy_client_peppol/i18n/fi.po
odoo/addons/account_edi_proxy_client_peppol/i18n/fr.po
odoo/addons/account_edi_proxy_client_peppol/i18n/he.po
odoo/addons/account_edi_proxy_client_peppol/i18n/hr.po
odoo/addons/account_edi_proxy_client_peppol/i18n/hu.po
odoo/addons/account_edi_proxy_client_peppol/i18n/hy.po
odoo/addons/account_edi_proxy_client_peppol/i18n/id.po
odoo/addons/account_edi_proxy_client_peppol/i18n/is.po
odoo/addons/account_edi_proxy_client_peppol/i18n/it.po
odoo/addons/account_edi_proxy_client_peppol/i18n/ja.po
odoo/addons/account_edi_proxy_client_peppol/i18n/ko.po
odoo/addons/account_edi_proxy_client_peppol/i18n/lt.po
odoo/addons/account_edi_proxy_client_peppol/i18n/lv.po
odoo/addons/account_edi_proxy_client_peppol/i18n/nb.po
odoo/addons/account_edi_proxy_client_peppol/i18n/nl.po
odoo/addons/account_edi_proxy_client_peppol/i18n/pl.po
odoo/addons/account_edi_proxy_client_peppol/i18n/pt.po
odoo/addons/account_edi_proxy_client_peppol/i18n/pt_BR.po
odoo_addon_account_edi_proxy_client_peppol-16.0.1.0.0.3.dist-info/METADATA
odoo_addon_account_edi_proxy_client_peppol-16.0.1.0.0.3.dist-info/WHEEL
odoo_addon_account_edi_proxy_client_peppol-16.0.1.0.0.3.dist-info/top_level.txt
odoo_addon_account_edi_proxy_client_peppol-16.0.1.0.0.3.dist-info/RECORD
