Metadata-Version: 2.1
Name: odoo-addon-account_edi_proxy_client_peppol
Version: 16.0.1.0.0.3
Requires-Python: >=3.10
Requires-Dist: cryptography
Requires-Dist: odoo>=16.0a,<16.1dev
Summary: Proxy features for the peppol access point
Home-page: https://github.com/acsone/odoo-peppol-backport
License: LGPL-3
Author: Odoo S.A.,ACSONE SA/NV,Odoo Community Association (OCA)
Author-email: support@odoo-community.org
Classifier: Programming Language :: Python
Classifier: Framework :: Odoo
Classifier: Framework :: Odoo :: 16.0
Classifier: License :: OSI Approved :: GNU Lesser General Public License v3 (LGPLv3)
